awstorm/__init__.py
awstorm/__main__.py
awstorm-0.0.1.dist-info/METADATA
awstorm-0.0.1.dist-info/WHEEL
awstorm-0.0.1.dist-info/top_level.txt
awstorm-0.0.1.dist-info/RECORD
