Metadata-Version: 2.1
Name: awstorm
Version: 0.0.1
Summary: A Package to generate AWS project skeletons
Home-page: https://github.com/edthamm/awstorm
Author: Eduard Thamm
Author-email: eduard.thamm@thammit.at
License: MIT
Platform: UNKNOWN
Classifier: License :: OSI Approved :: MIT License
Classifier: Programming Language :: Python :: 3
Classifier: Programming Language :: Python :: 3.7
